entityAgent/__init__.py
entityAgent/ollama_utils.py
entityAgent/platform_interaction.py
entityAgent/runtime.py
entityagent-0.1.3.dist-info/METADATA
entityagent-0.1.3.dist-info/WHEEL
entityagent-0.1.3.dist-info/entry_points.txt
entityagent-0.1.3.dist-info/top_level.txt
entityagent-0.1.3.dist-info/RECORD
