Metadata-Version: 2.4
Name: entityagent
Version: 0.1.3
Summary: Entity Agent: An AI assistant with platform interaction capabilities
Home-page: https://github.com/prakashsellathurai/entity
Author: Prakash Sellathurai
Author-email: prakashsellathurai@gmail.com
Project-URL: Source, https://github.com/prakashsellathurai/entity
Project-URL: Tracker, https://github.com/prakashsellathurai/entity/issues
Classifier: Programming Language :: Python :: 3
Classifier: Operating System :: OS Independent
Classifier: Intended Audience :: Developers
Classifier: License :: OSI Approved :: MIT License
Classifier: Topic :: Software Development :: Libraries :: Application Frameworks
Requires-Python: >=3.8
Requires-Dist: psutil
Dynamic: author
Dynamic: author-email
Dynamic: classifier
Dynamic: description
Dynamic: description-content-type
Dynamic: home-page
Dynamic: project-url
Dynamic: requires-dist
Dynamic: requires-python
Dynamic: summary
